dbtjumpstart/main.py
dbtjumpstart/setup.py
dbtjumpstart-0.1.6.dist-info/LICENSE
dbtjumpstart-0.1.6.dist-info/METADATA
dbtjumpstart-0.1.6.dist-info/WHEEL
dbtjumpstart-0.1.6.dist-info/top_level.txt
dbtjumpstart-0.1.6.dist-info/RECORD
