Metadata-Version: 2.1
Name: dbtjumpstart
Version: 0.1.6
Summary: A package to jumpstart a dbt project
Home-page: https://github.com/sahariprasad/dbt-jumpstart
Download-URL: https://github.com/sahariprasad/dbt-jumpstart/archive/refs/tags/v0.1.tar.gz
Author: Hari Prasad SA
Author-email: sahariprasad@outlook.com
License: MIT
Keywords: dbt,jumpstart
Classifier: Development Status :: 3 - Alpha
Classifier: Intended Audience :: Developers
Classifier: Topic :: Software Development :: Build Tools
Classifier: License :: OSI Approved :: MIT License
Classifier: Programming Language :: Python :: 3
Classifier: Programming Language :: Python :: 3.4
Classifier: Programming Language :: Python :: 3.5
Classifier: Programming Language :: Python :: 3.6
Classifier: Programming Language :: Python :: 3.7
Classifier: Programming Language :: Python :: 3.8
License-File: LICENSE
Requires-Dist: pandas
Requires-Dist: openpyxl
